Metadata-Version: 2.1
Name: gradio-frp
Version: 3.41.0.post1
Summary: Python library for easily interacting with trained machine learning models
Project-URL: Homepage, https://github.com/gradio-app/gradio
Author-email: Abubakar Abid <team@gradio.app>, Ali Abid <team@gradio.app>, Ali Abdalla <team@gradio.app>, Dawood Khan <team@gradio.app>, Ahsen Khaliq <team@gradio.app>, Pete Allen <team@gradio.app>, Ömer Faruk Özdemir <team@gradio.app>
License-Expression: Apache-2.0
License-File: LICENSE
Keywords: machine learning,reproducibility,visualization
Classifier: Development Status :: 5 - Production/Stable
Classifier: License :: OSI Approved :: Apache Software License
Classifier: Operating System :: OS Independent
Classifier: Programming Language :: Python :: 3
Classifier: Programming Language :: Python :: 3 :: Only
Classifier: Programming Language :: Python :: 3.8
Classifier: Programming Language :: Python :: 3.9
Classifier: Programming Language :: Python :: 3.10
Classifier: Programming Language :: Python :: 3.11
Classifier: Topic :: Scientific/Engineering
Classifier: Topic :: Scientific/Engineering :: Artificial Intelligence
Classifier: Topic :: Scientific/Engineering :: Visualization
Requires-Python: >=3.8
Requires-Dist: aiofiles<24.0,>=22.0
Requires-Dist: altair<6.0,>=4.2.0
Requires-Dist: fastapi
Requires-Dist: ffmpy
Requires-Dist: gradio-client==0.5.0
Requires-Dist: httpx
Requires-Dist: huggingface-hub>=0.14.0
Requires-Dist: importlib-resources<7.0,>=1.3
Requires-Dist: jinja2<4.0
Requires-Dist: markupsafe~=2.0
Requires-Dist: matplotlib~=3.0
Requires-Dist: numpy~=1.0
Requires-Dist: orjson~=3.0
Requires-Dist: packaging
Requires-Dist: pandas<3.0,>=1.0
Requires-Dist: pillow<11.0,>=8.0
Requires-Dist: pydantic!=1.8,!=1.8.1,!=2.0.0,!=2.0.1,<3.0.0,>=1.7.4
Requires-Dist: pydub
Requires-Dist: python-multipart
Requires-Dist: pyyaml<7.0,>=5.0
Requires-Dist: requests~=2.0
Requires-Dist: semantic-version~=2.0
Requires-Dist: typing-extensions~=4.0
Requires-Dist: uvicorn>=0.14.0
Requires-Dist: websockets<12.0,>=10.0
Provides-Extra: oauth
Requires-Dist: authlib; extra == 'oauth'
Requires-Dist: itsdangerous; extra == 'oauth'
